LICENSE.txt
MANIFEST.in
README.md
setup.py
cmsplugin_multipinmap/__init__.py
cmsplugin_multipinmap/cms_plugins.py
cmsplugin_multipinmap/models.py
cmsplugin_multipinmap/tests.py
cmsplugin_multipinmap.egg-info/PKG-INFO
cmsplugin_multipinmap.egg-info/SOURCES.txt
cmsplugin_multipinmap.egg-info/dependency_links.txt
cmsplugin_multipinmap.egg-info/requires.txt
cmsplugin_multipinmap.egg-info/top_level.txt
cmsplugin_multipinmap/migrations/0001_initial.py
cmsplugin_multipinmap/migrations/0002_pin_pin_color.py
cmsplugin_multipinmap/migrations/0003_auto_20150716_1725.py
cmsplugin_multipinmap/migrations/0004_auto_20151029_1821.py
cmsplugin_multipinmap/migrations/0005_auto_20151029_1824.py
cmsplugin_multipinmap/migrations/0006_auto_20151110_2046.py
cmsplugin_multipinmap/migrations/0007_auto_20151111_1021.py
cmsplugin_multipinmap/migrations/0008_auto_20151208_1044.py
cmsplugin_multipinmap/migrations/__init__.py
cmsplugin_multipinmap/static/cmsplugin_multipinmap/img/marker-icon-blue.png
cmsplugin_multipinmap/static/cmsplugin_multipinmap/img/marker-icon-green.png
cmsplugin_multipinmap/static/cmsplugin_multipinmap/img/marker-icon-red.png
cmsplugin_multipinmap/static/cmsplugin_multipinmap/img/marker-icon-yellow.png
cmsplugin_multipinmap/static/cmsplugin_multipinmap/img/marker-shadow.png
cmsplugin_multipinmap/templates/cmsplugin_multipinmap/google.html
cmsplugin_multipinmap/templates/cmsplugin_multipinmap/infowindow.html
cmsplugin_multipinmap/templates/cmsplugin_multipinmap/leaflet.html