Metadata-Version: 1.1
Name: cmsplugin-multipinmap
Version: 0.1.0
Summary: A djangocms carousel slider plugin.
Home-page: https://github.com/creimers/cmsplugin_multipinmap
Author: Christoph Reimers
Author-email: christoph@superservice-international.com
License: BSD License
Keywords: djangocms,django,map,plugin
Platform: UNKNOWN
Classifier: Operating System :: OS Independent
Classifier: Development Status :: 5 - Production/Stable
Classifier: Programming Language :: Python
Classifier: Framework :: Django
Classifier: Programming Language :: Python :: 2.7
Classifier: Programming Language :: Python :: 3.4
